sistema_bancario/__init__.py
sistema_bancario/sistema_bancario.py
rhyan_sistema_bancario-0.0.1.dist-info/METADATA
rhyan_sistema_bancario-0.0.1.dist-info/WHEEL
rhyan_sistema_bancario-0.0.1.dist-info/top_level.txt
rhyan_sistema_bancario-0.0.1.dist-info/RECORD
