Metadata-Version: 2.4
Name: rhyan-sistema_bancario
Version: 0.0.1
Summary: Sistema Bancário
Home-page: https://github.com/Rhyan121121/Sistema-Bancario-Para_Pypi
Author: Rhyan
Author-email: rhyanaa1211@gmail.com
Requires-Python: >=3.8
Requires-Dist: ABC
Requires-Dist: datetime
Requires-Dist: textwrap
Dynamic: author
Dynamic: author-email
Dynamic: description
Dynamic: description-content-type
Dynamic: home-page
Dynamic: requires-dist
Dynamic: requires-python
Dynamic: summary
